ash/__init__.py
ash/ash.py
ash/config.py
ash_williams-0.9.2.dist-info/LICENSE
ash_williams-0.9.2.dist-info/METADATA
ash_williams-0.9.2.dist-info/WHEEL
ash_williams-0.9.2.dist-info/top_level.txt
ash_williams-0.9.2.dist-info/RECORD
