Metadata-Version: 2.1
Name: ash-williams
Version: 0.9.2
Summary: Hunting Deadites in the references
Author-email: Matt VanEseltine <matvan@umich.edu>
License: GNU AFFERO GENERAL PUBLIC LICENSE
Project-URL: Homepage, https://github.com/vaneseltine/ash-williams
Project-URL: Repository, https://github.com/vaneseltine/ash-williams
Project-URL: Issues, https://github.com/vaneseltine/ash-williams/issues
Keywords: bibliography,citation,doi,publications,references,retraction,science
Classifier: Development Status :: 3 - Alpha
Classifier: Intended Audience :: Developers
Classifier: Intended Audience :: Science/Research
Classifier: License :: OSI Approved :: GNU Affero General Public License v3 or later (AGPLv3+)
Classifier: Natural Language :: English
Classifier: Operating System :: Microsoft :: Windows
Classifier: Operating System :: POSIX :: Linux
Classifier: Programming Language :: Python
Classifier: Programming Language :: Python :: 3.10
Classifier: Programming Language :: Python :: 3.11
Classifier: Programming Language :: Python :: 3.12
Classifier: Programming Language :: Python :: 3 :: Only
Classifier: Topic :: Scientific/Engineering
Classifier: Topic :: Scientific/Engineering :: Information Analysis
Classifier: Typing :: Typed
Requires-Python: >=3.10
License-File: LICENSE
Requires-Dist: filetype >=1.2.0
Requires-Dist: pypdf >=4.2.0
Requires-Dist: striprtf >=0.0.26
Requires-Dist: urllib3 >=2.2.2
